lil_nocap/.DS_Store
lil_nocap/.__init__.py.swp
lil_nocap/__init__.py
lil_nocap/opinions.jsonl
lil_nocap/test.py
lil_nocap/test.txt
lil_nocap-0.5.4.dist-info/WHEEL
lil_nocap-0.5.4.dist-info/entry_points.txt
lil_nocap-0.5.4.dist-info/METADATA
lil_nocap-0.5.4.dist-info/RECORD
