Metadata-Version: 2.1
Name: lil-nocap
Version: 0.5.4
Summary: A package for downloading bulk files from courtlistener
License: MIT
Author: sabzo
Author-email: sabelo@sabelo.io
Requires-Python: >=3.8,<4.0
Classifier: License :: OSI Approved :: MIT License
Classifier: Programming Language :: Python :: 3
Classifier: Programming Language :: Python :: 3.8
Classifier: Programming Language :: Python :: 3.9
Classifier: Programming Language :: Python :: 3.10
Classifier: Programming Language :: Python :: 3.11
Requires-Dist: click (>=8.1.3,<9.0.0)
Requires-Dist: dask[dataframe] (>=2023.3.0,<2024.0.0)
Requires-Dist: numpy (>=1.24.2,<2.0.0)
Requires-Dist: pandas (>=1.5.3,<2.0.0)
